wish_command_execution-0.6.28.dist-info/LICENSE
wish_command_execution-0.6.28.dist-info/METADATA
wish_command_execution-0.6.28.dist-info/WHEEL
wish_command_execution-0.6.28.dist-info/entry_points.txt
wish_command_execution/__init__.py
wish_command_execution/backend/__init__.py
wish_command_execution/backend/base.py
wish_command_execution/backend/bash.py
wish_command_execution/backend/factory.py
wish_command_execution/backend/sliver.py
wish_command_execution/command_executor.py
wish_command_execution/command_status_tracker.py
wish_command_execution/constants.py
wish_command_execution/system_info.py
wish_command_execution/utils/__init__.py
wish_command_execution/utils/log_utils.py
wish_command_execution-0.6.28.dist-info/RECORD
