Metadata-Version: 2.1
Name: wish-command-execution
Version: 0.6.28
Summary: Command execution package for wish
Keywords: wish,llm,ai,shell,command-execution
Author-Email: Security & Development Lab <lay.sakura+secdevlab@gmail.com>
Maintainer-Email: Sho Nakatani <lay.sakura@gmail.com>
License:                     GNU AFFERO GENERAL PUBLIC LICENSE
Classifier: Development Status :: 4 - Beta
Classifier: Intended Audience :: Developers
Classifier: Programming Language :: Python :: 3
Classifier: Programming Language :: Python :: 3.10
Classifier: Programming Language :: Python :: 3.11
Classifier: Programming Language :: Python :: 3.12
Classifier: Programming Language :: Python :: 3.13
Classifier: Topic :: Software Development :: Libraries
Classifier: Topic :: System :: Shells
Project-URL: Homepage, https://github.com/SecDev-Lab/wish
Project-URL: Documentation, https://github.com/SecDev-Lab/wish
Project-URL: Repository, https://github.com/SecDev-Lab/wish.git
Project-URL: Issues, https://github.com/SecDev-Lab/wish/issues
Requires-Python: >=3.10
Requires-Dist: wish-models==0.6.28
Requires-Dist: pydantic>=2.10.6
Requires-Dist: sliver-py>=0.0.19
Requires-Dist: wish-tools
